streamlit_file_browser/__init__.py
streamlit_file_browser/frontend/build/asset-manifest.json
streamlit_file_browser/frontend/build/bootstrap.min.css
streamlit_file_browser/frontend/build/index.html
streamlit_file_browser/frontend/build/precache-manifest.8e986bc7ba36592e6926912c62485e85.js
streamlit_file_browser/frontend/build/service-worker.js
streamlit_file_browser/frontend/build/static/css/2.5a3919a9.chunk.css
streamlit_file_browser/frontend/build/static/css/2.5a3919a9.chunk.css.map
streamlit_file_browser/frontend/build/static/js/2.1dbd9b27.chunk.js
streamlit_file_browser/frontend/build/static/js/2.1dbd9b27.chunk.js.LICENSE.txt
streamlit_file_browser/frontend/build/static/js/2.1dbd9b27.chunk.js.map
streamlit_file_browser/frontend/build/static/js/main.66c8bd0b.chunk.js
streamlit_file_browser/frontend/build/static/js/main.66c8bd0b.chunk.js.map
streamlit_file_browser/frontend/build/static/js/runtime-main.5606d314.js
streamlit_file_browser/frontend/build/static/js/runtime-main.5606d314.js.map
streamlit_file_browser/frontend/build/static/media/fontawesome-webfont.674f50d2.eot
streamlit_file_browser/frontend/build/static/media/fontawesome-webfont.912ec66d.svg
streamlit_file_browser/frontend/build/static/media/fontawesome-webfont.af7ae505.woff2
streamlit_file_browser/frontend/build/static/media/fontawesome-webfont.b06871f2.ttf
streamlit_file_browser/frontend/build/static/media/fontawesome-webfont.fee66e71.woff
streamlit_file_browser-1.0.4.dist-info/METADATA
streamlit_file_browser-1.0.4.dist-info/WHEEL
streamlit_file_browser-1.0.4.dist-info/top_level.txt
streamlit_file_browser-1.0.4.dist-info/RECORD
