Metadata-Version: 2.1
Name: streamlit-file-browser
Version: 1.0.4
Home-page: 
Author: 
Author-email: 
Requires-Python: >=3.6
Requires-Dist: pandas
Requires-Dist: filetype
Requires-Dist: streamlit-molstar
Requires-Dist: streamlit (>=0.63)
